<?xml version="1.0" encoding="UTF-8"?><ans:mensagemTISS xmlns:ans="http://www.ans.gov.br/padroes/tiss/schemas"><ans:loteGuias><ans:guiaResumoInternacao><ans:cabecalhoGuia><ans:registroANS>312345</ans:registroANS><ans:numeroGuiaPrestador>G00034</ans:numeroGuiaPrestador></ans:cabecalhoGuia><ans:dataInicioFaturamento>2025-04-19</ans:dataInicioFaturamento><ans:dataFinalFaturamento>2025-04-21</ans:dataFinalFaturamento><ans:diagnosticoCID>S72.0</ans:diagnosticoCID><ans:procedimentosExecutados><ans:procedimentoExecutado><ans:procedimento><ans:codigoProcedimento>31003079</ans:codigoProcedimento></ans:procedimento></ans:procedimentoExecutado><ans:procedimentoExecutado><ans:procedimento><ans:codigoProcedimento>41001010</ans:codigoProcedimento></ans:procedimento></ans:procedimentoExecutado><ans:procedimentoExecutado><ans:procedimento><ans:codigoProcedimento>41001010</ans:codigoProcedimento></ans:procedimento></ans:procedimentoExecutado><ans:procedimentoExecutado><ans:procedimento><ans:codigoProcedimento>30912016</ans:codigoProcedimento></ans:procedimento></ans:procedimentoExecutado><ans:procedimentoExecutado><ans:procedimento><ans:codigoProcedimento>30912016</ans:codigoProcedimento></ans:procedimento></ans:procedimentoExecutado></ans:procedimentosExecutados><ans:valorTotal><ans:valorOPME>1069.88</ans:valorOPME><ans:valorTotalGeral>17318.25</ans:valorTotalGeral></ans:valorTotal></ans:guiaResumoInternacao><ans:guiaResumoInternacao><ans:cabecalhoGuia><ans:registroANS>312345</ans:registroANS><ans:numeroGuiaPrestador>G00015</ans:numeroGuiaPrestador></ans:cabecalhoGuia><ans:dataInicioFaturamento>2025-03-03</ans:dataInicioFaturamento><ans:dataFinalFaturamento>2025-03-21</ans:dataFinalFaturamento><ans:diagnosticoCID>O80</ans:diagnosticoCID><ans:procedimentosExecutados><ans:procedimentoExecutado><ans:procedimento><ans:codigoProcedimento>31003079</ans:codigoProcedimento></ans:procedimento></ans:procedimentoExecutado><ans:procedimentoExecutado><ans:procedimento><ans:codigoProcedimento>30715016</ans:codigoProcedimento></ans:procedimento></ans:procedimentoExecutado><ans:procedimentoExecutado><ans:procedimento><ans:codigoProcedimento>30912016</ans:codigoProcedimento></ans:procedimento></ans:procedimentoExecutado><ans:procedimentoExecutado><ans:procedimento><ans:codigoProcedimento>41001010</ans:codigoProcedimento></ans:procedimento></ans:procedimentoExecutado><ans:procedimentoExecutado><ans:procedimento><ans:codigoProcedimento>40803104</ans:codigoProcedimento></ans:procedimento></ans:procedimentoExecutado><ans:procedimentoExecutado><ans:procedimento><ans:codigoProcedimento>41001010</ans:codigoProcedimento></ans:procedimento></ans:procedimentoExecutado><ans:procedimentoExecutado><ans:procedimento><ans:codigoProcedimento>31005497</ans:codigoProcedimento></ans:procedimento></ans:procedimentoExecutado><ans:procedimentoExecutado><ans:procedimento><ans:codigoProcedimento>40304361</ans:codigoProcedimento></ans:procedimento></ans:procedimentoExecutado><ans:procedimentoExecutado><ans:procedimento><ans:codigoProcedimento>40304361</ans:codigoProcedimento></ans:procedimento></ans:procedimentoExecutado><ans:procedimentoExecutado><ans:procedimento><ans:codigoProcedimento>30715016</ans:codigoProcedimento></ans:procedimento></ans:procedimentoExecutado><ans:procedimentoExecutado><ans:procedimento><ans:codigoProcedimento>41001010</ans:codigoProcedimento></ans:procedimento></ans:procedimentoExecutado><ans:procedimentoExecutado><ans:procedimento><ans:codigoProcedimento>31005497</ans:codigoProcedimento></ans:procedimento></ans:procedimentoExecutado><ans:procedimentoExecutado><ans:procedimento><ans:codigoProcedimento>31101011</ans:codigoProcedimento></ans:procedimento></ans:procedimentoExecutado><ans:procedimentoExecutado><ans:procedimento><ans:codigoProcedimento>30213036</ans:codigoProcedimento></ans:procedimento></ans:procedimentoExecutado></ans:procedimentosExecutados><ans:valorTotal><ans:valorOPME>0.85</ans:valorOPME><ans:valorTotalGeral>17023.83</ans:valorTotalGeral></ans:valorTotal></ans:guiaResumoInternacao><ans:guiaResumoInternacao><ans:cabecalhoGuia><ans:registroANS>312345</ans:registroANS><ans:numeroGuiaPrestador>G00035</ans:numeroGuiaPrestador></ans:cabecalhoGuia><ans:dataInicioFaturamento>2025-04-09</ans:dataInicioFaturamento><ans:dataFinalFaturamento>2025-04-15</ans:dataFinalFaturamento><ans:diagnosticoCID><ans:codigoDiagnostico>C34.9</ans:codigoDiagnostico></ans:diagnosticoCID><ans:procedimentosExecutados><ans:procedimentoExecutado><ans:procedimento><ans:codigoProcedimento>31003079</ans:codigoProcedimento></ans:procedimento></ans:procedimentoExecutado><ans:procedimentoExecutado><ans:procedimento><ans:codigoProcedimento>30715016</ans:codigoProcedimento></ans:procedimento></ans:procedimentoExecutado><ans:procedimentoExecutado><ans:procedimento><ans:codigoProcedimento>30213036</ans:codigoProcedimento></ans:procedimento></ans:procedimentoExecutado><ans:procedimentoExecutado><ans:procedimento><ans:codigoProcedimento>40803104</ans:codigoProcedimento></ans:procedimento></ans:procedimentoExecutado><ans:procedimentoExecutado><ans:procedimento><ans:codigoProcedimento>30912016</ans:codigoProcedimento></ans:procedimento></ans:procedimentoExecutado><ans:procedimentoExecutado><ans:procedimento><ans:codigoProcedimento>40304361</ans:codigoProcedimento></ans:procedimento></ans:procedimentoExecutado><ans:procedimentoExecutado><ans:procedimento><ans:codigoProcedimento>30912016</ans:codigoProcedimento></ans:procedimento></ans:procedimentoExecutado><ans:procedimentoExecutado><ans:procedimento><ans:codigoProcedimento>31101011</ans:codigoProcedimento></ans:procedimento></ans:procedimentoExecutado></ans:procedimentosExecutados><ans:valorTotal><ans:valorOPME>28.80</ans:valorOPME><ans:valorTotalGeral>8928.04</ans:valorTotalGeral></ans:valorTotal></ans:guiaResumoInternacao><ans:guiaResumoInternacao><ans:cabecalhoGuia><ans:registroANS>312345</ans:registroANS><ans:numeroGuiaPrestador>G00036</ans:numeroGuiaPrestador></ans:cabecalhoGuia><ans:dataInicioFaturamento>2025-04-18</ans:dataInicioFaturamento><ans:dataFinalFaturamento>2025-04-21</ans:dataFinalFaturamento><ans:diagnosticoCID>I63.9</ans:diagnosticoCID><ans:procedimentosExecutados><ans:procedimentoExecutado><ans:procedimento><ans:codigoProcedimento>31005497</ans:codigoProcedimento></ans:procedimento></ans:procedimentoExecutado><ans:procedimentoExecutado><ans:procedimento><ans:codigoProcedimento>41001010</ans:codigoProcedimento></ans:procedimento></ans:procedimentoExecutado><ans:procedimentoExecutado><ans:procedimento><ans:codigoProcedimento>30912016</ans:codigoProcedimento></ans:procedimento></ans:procedimentoExecutado><ans:procedimentoExecutado><ans:procedimento><ans:codigoProcedimento>40803104</ans:codigoProcedimento></ans:procedimento></ans:procedimentoExecutado><ans:procedimentoExecutado><ans:procedimento><ans:codigoProcedimento>31005497</ans:codigoProcedimento></ans:procedimento></ans:procedimentoExecutado><ans:procedimentoExecutado><ans:procedimento><ans:codigoProcedimento>31602096</ans:codigoProcedimento></ans:procedimento></ans:procedimentoExecutado><ans:procedimentoExecutado><ans:procedimento><ans:codigoProcedimento>41001010</ans:codigoProcedimento></ans:procedimento></ans:procedimentoExecutado><ans:procedimentoExecutado><ans:procedimento><ans:codigoProcedimento>31101011</ans:codigoProcedimento></ans:procedimento></ans:procedimentoExecutado><ans:procedimentoExecutado><ans:procedimento><ans:codigoProcedimento>30213036</ans:codigoProcedimento></ans:procedimento></ans:procedimentoExecutado><ans:procedimentoExecutado><ans:procedimento><ans:codigoProcedimento>30912016</ans:codigoProcedimento></ans:procedimento></ans:procedimentoExecutado></ans:procedimentosExecutados><ans:valorTotal><ans:valorOPME>975.13</ans:valorOPME><ans:valorTotalGeral>3524.82</ans:valorTotalGeral></ans:valorTotal></ans:guiaResumoInternacao><ans:guiaResumoInternacao><ans:cabecalhoGuia><ans:registroANS>312345</ans:registroANS><ans:numeroGuiaPrestador>G00037</ans:numeroGuiaPrestador></ans:cabecalhoGuia><ans:dataInicioFaturamento>2025-04-20</ans:dataInicioFaturamento><ans:dataFinalFaturamento>2025-04-28</ans:dataFinalFaturamento><ans:diagnosticoCID>A41.9</ans:diagnosticoCID><ans:procedimentosExecutados><ans:procedimentoExecutado><ans:procedimento><ans:codigoProcedimento>31602096</ans:codigoProcedimento></ans:procedimento></ans:procedimentoExecutado><ans:procedimentoExecutado><ans:procedimento><ans:codigoProcedimento>40304361</ans:codigoProcedimento></ans:procedimento></ans:procedimentoExecutado><ans:procedimentoExecutado><ans:procedimento><ans:codigoProcedimento>30912016</ans:codigoProcedimento></ans:procedimento></ans:procedimentoExecutado><ans:procedimentoExecutado><ans:procedimento><ans:codigoProcedimento>40304361</ans:codigoProcedimento></ans:procedimento></ans:procedimentoExecutado><ans:procedimentoExecutado><ans:procedimento><ans:codigoProcedimento>30715016</ans:codigoProcedimento></ans:procedimento></ans:procedimentoExecutado><ans:procedimentoExecutado><ans:procedimento><ans:codigoProcedimento>30912016</ans:codigoProcedimento></ans:procedimento></ans:procedimentoExecutado><ans:procedimentoExecutado><ans:procedimento><ans:codigoProcedimento>31003079</ans:codigoProcedimento></ans:procedimento></ans:procedimentoExecutado><ans:procedimentoExecutado><ans:procedimento><ans:codigoProcedimento>41001010</ans:codigoProcedimento></ans:procedimento></ans:procedimentoExecutado></ans:procedimentosExecutados><ans:valorTotal><ans:valorOPME>480.70</ans:valorOPME><ans:valorTotalGeral>26698.68</ans:valorTotalGeral></ans:valorTotal></ans:guiaResumoInternacao><ans:guiaResumoInternacao><ans:cabecalhoGuia><ans:registroANS>312345</ans:registroANS><ans:numeroGuiaPrestador>G00038</ans:numeroGuiaPrestador></ans:cabecalhoGuia><ans:dataInicioFaturamento>2025-04-05</ans:dataInicioFaturamento><ans:dataFinalFaturamento>2025-04-07</ans:dataFinalFaturamento><ans:diagnosticoCID>I50.0</ans:diagnosticoCID><ans:procedimentosExecutados><ans:procedimentoExecutado><ans:procedimento><ans:codigoProcedimento>41001010</ans:codigoProcedimento></ans:procedimento></ans:procedimentoExecutado><ans:procedimentoExecutado><ans:procedimento><ans:codigoProcedimento>31003079</ans:codigoProcedimento></ans:procedimento></ans:procedimentoExecutado><ans:procedimentoExecutado><ans:procedimento><ans:codigoProcedimento>31005497</ans:codigoProcedimento></ans:procedimento></ans:procedimentoExecutado><ans:procedimentoExecutado><ans:procedimento><ans:codigoProcedimento>31003079</ans:codigoProcedimento></ans:procedimento></ans:procedimentoExecutado><ans:procedimentoExecutado><ans:procedimento><ans:codigoProcedimento>31003079</ans:codigoProcedimento></ans:procedimento></ans:procedimentoExecutado></ans:procedimentosExecutados><ans:valorTotal><ans:valorOPME>3493.31</ans:valorOPME><ans:valorTotalGeral>11808.51</ans:valorTotalGeral></ans:valorTotal></ans:guiaResumoInternacao><ans:guiaResumoInternacao><ans:cabecalhoGuia><ans:registroANS>312345</ans:registroANS><ans:numeroGuiaPrestador>G00039</ans:numeroGuiaPrestador></ans:cabecalhoGuia><ans:dataInicioFaturamento>2025-04-13</ans:dataInicioFaturamento><ans:dataFinalFaturamento>2025-04-16</ans:dataFinalFaturamento><ans:diagnosticoCID>J18.9</ans:diagnosticoCID><ans:procedimentosExecutados><ans:procedimentoExecutado><ans:procedimento><ans:codigoProcedimento>31602096</ans:codigoProcedimento></ans:procedimento></ans:procedimentoExecutado><ans:procedimentoExecutado><ans:procedimento><ans:codigoProcedimento>40803104</ans:codigoProcedimento></ans:procedimento></ans:procedimentoExecutado><ans:procedimentoExecutado><ans:procedimento><ans:codigoProcedimento>31005497</ans:codigoProcedimento></ans:procedimento></ans:procedimentoExecutado><ans:procedimentoExecutado><ans:procedimento><ans:codigoProcedimento>31101011</ans:codigoProcedimento></ans:procedimento></ans:procedimentoExecutado><ans:procedimentoExecutado><ans:procedimento><ans:codigoProcedimento>30912016</ans:codigoProcedimento></ans:procedimento></ans:procedimentoExecutado><ans:procedimentoExecutado><ans:procedimento><ans:codigoProcedimento>40803104</ans:codigoProcedimento></ans:procedimento></ans:procedimentoExecutado><ans:procedimentoExecutado><ans:procedimento><ans:codigoProcedimento>40803104</ans:codigoProcedimento></ans:procedimento></ans:procedimentoExecutado></ans:procedimentosExecutados><ans:valorTotal><ans:valorOPME>19.77</ans:valorOPME><ans:valorTotalGeral>4906.63</ans:valorTotalGeral></ans:valorTotal></ans:guiaResumoInternacao><ans:guiaResumoInternacao><ans:cabecalhoGuia><ans:registroANS>312345</ans:registroANS><ans:numeroGuiaPrestador>G00040</ans:numeroGuiaPrestador></ans:cabecalhoGuia><ans:dataInicioFaturamento>2025-04-05</ans:dataInicioFaturamento><ans:dataFinalFaturamento>2025-04-10</ans:dataFinalFaturamento><ans:diagnosticoCID>N39.0</ans:diagnosticoCID><ans:procedimentosExecutados><ans:procedimentoExecutado><ans:procedimento><ans:codigoProcedimento>31101011</ans:codigoProcedimento></ans:procedimento></ans:procedimentoExecutado><ans:procedimentoExecutado><ans:procedimento><ans:codigoProcedimento>30213036</ans:codigoProcedimento></ans:procedimento></ans:procedimentoExecutado><ans:procedimentoExecutado><ans:procedimento><ans:codigoProcedimento>40803104</ans:codigoProcedimento></ans:procedimento></ans:procedimentoExecutado><ans:procedimentoExecutado><ans:procedimento><ans:codigoProcedimento>40304361</ans:codigoProcedimento></ans:procedimento></ans:procedimentoExecutado><ans:procedimentoExecutado><ans:procedimento><ans:codigoProcedimento>31101011</ans:codigoProcedimento></ans:procedimento></ans:procedimentoExecutado><ans:procedimentoExecutado><ans:procedimento><ans:codigoProcedimento>41001010</ans:codigoProcedimento></ans:procedimento></ans:procedimentoExecutado><ans:procedimentoExecutado><ans:procedimento><ans:codigoProcedimento>40803104</ans:codigoProcedimento></ans:procedimento></ans:procedimentoExecutado></ans:procedimentosExecutados><ans:valorTotal><ans:valorOPME>8.01</ans:valorOPME><ans:valorTotalGeral>3631.44</ans:valorTotalGeral></ans:valorTotal></ans:guiaResumoInternacao><ans:guiaResumoInternacao><ans:cabecalhoGuia><ans:registroANS>312345</ans:registroANS><ans:numeroGuiaPrestador>G00041</ans:numeroGuiaPrestador></ans:cabecalhoGuia><ans:dataInicioFaturamento>2025-04-10</ans:dataInicioFaturamento><ans:dataFinalFaturamento>2025-04-13</ans:dataFinalFaturamento><ans:diagnosticoCID><ans:codigoDiagnostico>J18.9</ans:codigoDiagnostico></ans:diagnosticoCID><ans:procedimentosExecutados><ans:procedimentoExecutado><ans:procedimento><ans:codigoProcedimento>31005497</ans:codigoProcedimento></ans:procedimento></ans:procedimentoExecutado><ans:procedimentoExecutado><ans:procedimento><ans:codigoProcedimento>31101011</ans:codigoProcedimento></ans:procedimento></ans:procedimentoExecutado><ans:procedimentoExecutado><ans:procedimento><ans:codigoProcedimento>31005497</ans:codigoProcedimento></ans:procedimento></ans:procedimentoExecutado><ans:procedimentoExecutado><ans:procedimento><ans:codigoProcedimento>31003079</ans:codigoProcedimento></ans:procedimento></ans:procedimentoExecutado><ans:procedimentoExecutado><ans:procedimento><ans:codigoProcedimento>31101011</ans:codigoProcedimento></ans:procedimento></ans:procedimentoExecutado><ans:procedimentoExecutado><ans:procedimento><ans:codigoProcedimento>31101011</ans:codigoProcedimento></ans:procedimento></ans:procedimentoExecutado><ans:procedimentoExecutado><ans:procedimento><ans:codigoProcedimento>40803104</ans:codigoProcedimento></ans:procedimento></ans:procedimentoExecutado></ans:procedimentosExecutados><ans:valorTotal><ans:valorOPME>740.84</ans:valorOPME><ans:valorTotalGeral>4850.91</ans:valorTotalGeral></ans:valorTotal></ans:guiaResumoInternacao><ans:guiaResumoInternacao><ans:cabecalhoGuia><ans:registroANS>312345</ans:registroANS><ans:numeroGuiaPrestador>G00042</ans:numeroGuiaPrestador></ans:cabecalhoGuia><ans:dataInicioFaturamento>2025-04-08</ans:dataInicioFaturamento><ans:dataFinalFaturamento>2025-04-14</ans:dataFinalFaturamento><ans:diagnosticoCID>A41.9</ans:diagnosticoCID><ans:procedimentosExecutados><ans:procedimentoExecutado><ans:procedimento><ans:codigoProcedimento>31005497</ans:codigoProcedimento></ans:procedimento></ans:procedimentoExecutado><ans:procedimentoExecutado><ans:procedimento><ans:codigoProcedimento>30912016</ans:codigoProcedimento></ans:procedimento></ans:procedimentoExecutado><ans:procedimentoExecutado><ans:procedimento><ans:codigoProcedimento>31003079</ans:codigoProcedimento></ans:procedimento></ans:procedimentoExecutado><ans:procedimentoExecutado><ans:procedimento><ans:codigoProcedimento>41001010</ans:codigoProcedimento></ans:procedimento></ans:procedimentoExecutado><ans:procedimentoExecutado><ans:procedimento><ans:codigoProcedimento>30715016</ans:codigoProcedimento></ans:procedimento></ans:procedimentoExecutado><ans:procedimentoExecutado><ans:procedimento><ans:codigoProcedimento>40304361</ans:codigoProcedimento></ans:procedimento></ans:procedimentoExecutado><ans:procedimentoExecutado><ans:procedimento><ans:codigoProcedimento>30912016</ans:codigoProcedimento></ans:procedimento></ans:procedimentoExecutado><ans:procedimentoExecutado><ans:procedimento><ans:codigoProcedimento>31101011</ans:codigoProcedimento></ans:procedimento></ans:procedimentoExecutado><ans:procedimentoExecutado><ans:procedimento><ans:codigoProcedimento>30213036</ans:codigoProcedimento></ans:procedimento></ans:procedimentoExecutado></ans:procedimentosExecutados><ans:valorTotal><ans:valorOPME>40.44</ans:valorOPME><ans:valorTotalGeral>5384.93</ans:valorTotalGeral></ans:valorTotal></ans:guiaResumoInternacao><ans:guiaResumoInternacao><ans:cabecalhoGuia><ans:registroANS>312345</ans:registroANS><ans:numeroGuiaPrestador>G00043</ans:numeroGuiaPrestador></ans:cabecalhoGuia><ans:dataInicioFaturamento>2025-04-08</ans:dataInicioFaturamento><ans:dataFinalFaturamento>2025-04-12</ans:dataFinalFaturamento><ans:diagnosticoCID><ans:codigoDiagnostico>I50.0</ans:codigoDiagnostico></ans:diagnosticoCID><ans:procedimentosExecutados><ans:procedimentoExecutado><ans:procedimento><ans:codigoProcedimento>31005497</ans:codigoProcedimento></ans:procedimento></ans:procedimentoExecutado><ans:procedimentoExecutado><ans:procedimento><ans:codigoProcedimento>30213036</ans:codigoProcedimento></ans:procedimento></ans:procedimentoExecutado><ans:procedimentoExecutado><ans:procedimento><ans:codigoProcedimento>30912016</ans:codigoProcedimento></ans:procedimento></ans:procedimentoExecutado><ans:procedimentoExecutado><ans:procedimento><ans:codigoProcedimento>31003079</ans:codigoProcedimento></ans:procedimento></ans:procedimentoExecutado><ans:procedimentoExecutado><ans:procedimento><ans:codigoProcedimento>31602096</ans:codigoProcedimento></ans:procedimento></ans:procedimentoExecutado></ans:procedimentosExecutados><ans:valorTotal><ans:valorOPME>63.43</ans:valorOPME><ans:valorTotalGeral>4081.67</ans:valorTotalGeral></ans:valorTotal></ans:guiaResumoInternacao><ans:guiaResumoInternacao><ans:cabecalhoGuia><ans:registroANS>312345</ans:registroANS><ans:numeroGuiaPrestador>G00044</ans:numeroGuiaPrestador></ans:cabecalhoGuia><ans:dataInicioFaturamento>2025-04-05</ans:dataInicioFaturamento><ans:dataFinalFaturamento>2025-04-15</ans:dataFinalFaturamento><ans:diagnosticoCID><ans:codigoDiagnostico>N39.0</ans:codigoDiagnostico></ans:diagnosticoCID><ans:procedimentosExecutados><ans:procedimentoExecutado><ans:procedimento><ans:codigoProcedimento>30213036</ans:codigoProcedimento></ans:procedimento></ans:procedimentoExecutado><ans:procedimentoExecutado><ans:procedimento><ans:codigoProcedimento>31101011</ans:codigoProcedimento></ans:procedimento></ans:procedimentoExecutado><ans:procedimentoExecutado><ans:procedimento><ans:codigoProcedimento>30715016</ans:codigoProcedimento></ans:procedimento></ans:procedimentoExecutado><ans:procedimentoExecutado><ans:procedimento><ans:codigoProcedimento>40304361</ans:codigoProcedimento></ans:procedimento></ans:procedimentoExecutado><ans:procedimentoExecutado><ans:procedimento><ans:codigoProcedimento>31003079</ans:codigoProcedimento></ans:procedimento></ans:procedimentoExecutado><ans:procedimentoExecutado><ans:procedimento><ans:codigoProcedimento>31101011</ans:codigoProcedimento></ans:procedimento></ans:procedimentoExecutado><ans:procedimentoExecutado><ans:procedimento><ans:codigoProcedimento>40803104</ans:codigoProcedimento></ans:procedimento></ans:procedimentoExecutado><ans:procedimentoExecutado><ans:procedimento><ans:codigoProcedimento>30715016</ans:codigoProcedimento></ans:procedimento></ans:procedimentoExecutado><ans:procedimentoExecutado><ans:procedimento><ans:codigoProcedimento>31602096</ans:codigoProcedimento></ans:procedimento></ans:procedimentoExecutado><ans:procedimentoExecutado><ans:procedimento><ans:codigoProcedimento>30715016</ans:codigoProcedimento></ans:procedimento></ans:procedimentoExecutado><ans:procedimentoExecutado><ans:procedimento><ans:codigoProcedimento>41001010</ans:codigoProcedimento></ans:procedimento></ans:procedimentoExecutado></ans:procedimentosExecutados><ans:valorTotal><ans:valorOPME>6834.78</ans:valorOPME><ans:valorTotalGeral>42187.99</ans:valorTotalGeral></ans:valorTotal></ans:guiaResumoInternacao><ans:guiaResumoInternacao><ans:cabecalhoGuia><ans:registroANS>312345</ans:registroANS><ans:numeroGuiaPrestador>G00045</ans:numeroGuiaPrestador></ans:cabecalhoGuia><ans:dataInicioFaturamento>2025-04-11</ans:dataInicioFaturamento><ans:dataFinalFaturamento>2025-04-16</ans:dataFinalFaturamento><ans:diagnosticoCID><ans:codigoDiagnostico>I63.9</ans:codigoDiagnostico></ans:diagnosticoCID><ans:procedimentosExecutados><ans:procedimentoExecutado><ans:procedimento><ans:codigoProcedimento>40803104</ans:codigoProcedimento></ans:procedimento></ans:procedimentoExecutado><ans:procedimentoExecutado><ans:procedimento><ans:codigoProcedimento>41001010</ans:codigoProcedimento></ans:procedimento></ans:procedimentoExecutado><ans:procedimentoExecutado><ans:procedimento><ans:codigoProcedimento>31101011</ans:codigoProcedimento></ans:procedimento></ans:procedimentoExecutado><ans:procedimentoExecutado><ans:procedimento><ans:codigoProcedimento>40304361</ans:codigoProcedimento></ans:procedimento></ans:procedimentoExecutado><ans:procedimentoExecutado><ans:procedimento><ans:codigoProcedimento>40803104</ans:codigoProcedimento></ans:procedimento></ans:procedimentoExecutado><ans:procedimentoExecutado><ans:procedimento><ans:codigoProcedimento>31005497</ans:codigoProcedimento></ans:procedimento></ans:procedimentoExecutado><ans:procedimentoExecutado><ans:procedimento><ans:codigoProcedimento>31003079</ans:codigoProcedimento></ans:procedimento></ans:procedimentoExecutado><ans:procedimentoExecutado><ans:procedimento><ans:codigoProcedimento>41001010</ans:codigoProcedimento></ans:procedimento></ans:procedimentoExecutado><ans:procedimentoExecutado><ans:procedimento><ans:codigoProcedimento>40304361</ans:codigoProcedimento></ans:procedimento></ans:procedimentoExecutado></ans:procedimentosExecutados><ans:valorTotal><ans:valorOPME>3.37</ans:valorOPME><ans:valorTotalGeral>13141.06</ans:valorTotalGeral></ans:valorTotal></ans:guiaResumoInternacao><ans:guiaResumoInternacao><ans:cabecalhoGuia><ans:registroANS>312345</ans:registroANS><ans:numeroGuiaPrestador>G00046</ans:numeroGuiaPrestador></ans:cabecalhoGuia><ans:dataInicioFaturamento>2025-04-16</ans:dataInicioFaturamento><ans:dataFinalFaturamento>2025-04-20</ans:dataFinalFaturamento><ans:diagnosticoCID>I21.0</ans:diagnosticoCID><ans:procedimentosExecutados><ans:procedimentoExecutado><ans:procedimento><ans:codigoProcedimento>31003079</ans:codigoProcedimento></ans:procedimento></ans:procedimentoExecutado><ans:procedimentoExecutado><ans:procedimento><ans:codigoProcedimento>40803104</ans:codigoProcedimento></ans:procedimento></ans:procedimentoExecutado><ans:procedimentoExecutado><ans:procedimento><ans:codigoProcedimento>40304361</ans:codigoProcedimento></ans:procedimento></ans:procedimentoExecutado><ans:procedimentoExecutado><ans:procedimento><ans:codigoProcedimento>30715016</ans:codigoProcedimento></ans:procedimento></ans:procedimentoExecutado><ans:procedimentoExecutado><ans:procedimento><ans:codigoProcedimento>31005497</ans:codigoProcedimento></ans:procedimento></ans:procedimentoExecutado></ans:procedimentosExecutados><ans:valorTotal><ans:valorOPME>108.22</ans:valorOPME><ans:valorTotalGeral>16627.24</ans:valorTotalGeral></ans:valorTotal></ans:guiaResumoInternacao><ans:guiaResumoInternacao><ans:cabecalhoGuia><ans:registroANS>312345</ans:registroANS><ans:numeroGuiaPrestador>G00047</ans:numeroGuiaPrestador></ans:cabecalhoGuia><ans:dataInicioFaturamento>2025-04-18</ans:dataInicioFaturamento><ans:dataFinalFaturamento>2025-04-22</ans:dataFinalFaturamento><ans:diagnosticoCID><ans:codigoDiagnostico>K35.8</ans:codigoDiagnostico></ans:diagnosticoCID><ans:procedimentosExecutados><ans:procedimentoExecutado><ans:procedimento><ans:codigoProcedimento>30912016</ans:codigoProcedimento></ans:procedimento></ans:procedimentoExecutado><ans:procedimentoExecutado><ans:procedimento><ans:codigoProcedimento>30213036</ans:codigoProcedimento></ans:procedimento></ans:procedimentoExecutado><ans:procedimentoExecutado><ans:procedimento><ans:codigoProcedimento>40803104</ans:codigoProcedimento></ans:procedimento></ans:procedimentoExecutado><ans:procedimentoExecutado><ans:procedimento><ans:codigoProcedimento>31003079</ans:codigoProcedimento></ans:procedimento></ans:procedimentoExecutado><ans:procedimentoExecutado><ans:procedimento><ans:codigoProcedimento>31005497</ans:codigoProcedimento></ans:procedimento></ans:procedimentoExecutado><ans:procedimentoExecutado><ans:procedimento><ans:codigoProcedimento>31101011</ans:codigoProcedimento></ans:procedimento></ans:procedimentoExecutado></ans:procedimentosExecutados><ans:valorTotal><ans:valorOPME>7.41</ans:valorOPME><ans:valorTotalGeral>3345.99</ans:valorTotalGeral></ans:valorTotal></ans:guiaResumoInternacao><ans:guiaResumoInternacao><ans:cabecalhoGuia><ans:registroANS>312345</ans:registroANS><ans:numeroGuiaPrestador>G00048</ans:numeroGuiaPrestador></ans:cabecalhoGuia><ans:dataInicioFaturamento>2025-04-12</ans:dataInicioFaturamento><ans:dataFinalFaturamento>2025-04-18</ans:dataFinalFaturamento><ans:diagnosticoCID><ans:codigoDiagnostico>K35.8</ans:codigoDiagnostico></ans:diagnosticoCID><ans:procedimentosExecutados><ans:procedimentoExecutado><ans:procedimento><ans:codigoProcedimento>30213036</ans:codigoProcedimento></ans:procedimento></ans:procedimentoExecutado><ans:procedimentoExecutado><ans:procedimento><ans:codigoProcedimento>31005497</ans:codigoProcedimento></ans:procedimento></ans:procedimentoExecutado><ans:procedimentoExecutado><ans:procedimento><ans:codigoProcedimento>31005497</ans:codigoProcedimento></ans:procedimento></ans:procedimentoExecutado><ans:procedimentoExecutado><ans:procedimento><ans:codigoProcedimento>31101011</ans:codigoProcedimento></ans:procedimento></ans:procedimentoExecutado><ans:procedimentoExecutado><ans:procedimento><ans:codigoProcedimento>31602096</ans:codigoProcedimento></ans:procedimento></ans:procedimentoExecutado><ans:procedimentoExecutado><ans:procedimento><ans:codigoProcedimento>30715016</ans:codigoProcedimento></ans:procedimento></ans:procedimentoExecutado><ans:procedimentoExecutado><ans:procedimento><ans:codigoProcedimento>30213036</ans:codigoProcedimento></ans:procedimento></ans:procedimentoExecutado></ans:procedimentosExecutados><ans:valorTotal><ans:valorOPME>1158.92</ans:valorOPME><ans:valorTotalGeral>2128.13</ans:valorTotalGeral></ans:valorTotal></ans:guiaResumoInternacao><ans:guiaResumoInternacao><ans:cabecalhoGuia><ans:registroANS>312345</ans:registroANS><ans:numeroGuiaPrestador>G00049</ans:numeroGuiaPrestador></ans:cabecalhoGuia><ans:dataInicioFaturamento>2025-04-20</ans:dataInicioFaturamento><ans:dataFinalFaturamento>2025-04-23</ans:dataFinalFaturamento><ans:diagnosticoCID>I50.0</ans:diagnosticoCID><ans:procedimentosExecutados><ans:procedimentoExecutado><ans:procedimento><ans:codigoProcedimento>31005497</ans:codigoProcedimento></ans:procedimento></ans:procedimentoExecutado><ans:procedimentoExecutado><ans:procedimento><ans:codigoProcedimento>30715016</ans:codigoProcedimento></ans:procedimento></ans:procedimentoExecutado><ans:procedimentoExecutado><ans:procedimento><ans:codigoProcedimento>31005497</ans:codigoProcedimento></ans:procedimento></ans:procedimentoExecutado><ans:procedimentoExecutado><ans:procedimento><ans:codigoProcedimento>31101011</ans:codigoProcedimento></ans:procedimento></ans:procedimentoExecutado><ans:procedimentoExecutado><ans:procedimento><ans:codigoProcedimento>31602096</ans:codigoProcedimento></ans:procedimento></ans:procedimentoExecutado></ans:procedimentosExecutados><ans:valorTotal><ans:valorOPME>27.32</ans:valorOPME><ans:valorTotalGeral>2891.24</ans:valorTotalGeral></ans:valorTotal></ans:guiaResumoInternacao><ans:guiaResumoInternacao><ans:cabecalhoGuia><ans:registroANS>312345</ans:registroANS><ans:numeroGuiaPrestador>G00050</ans:numeroGuiaPrestador></ans:cabecalhoGuia><ans:dataInicioFaturamento>2025-04-12</ans:dataInicioFaturamento><ans:dataFinalFaturamento>2025-04-21</ans:dataFinalFaturamento><ans:diagnosticoCID>N39.0</ans:diagnosticoCID><ans:procedimentosExecutados><ans:procedimentoExecutado><ans:procedimento><ans:codigoProcedimento>41001010</ans:codigoProcedimento></ans:procedimento></ans:procedimentoExecutado><ans:procedimentoExecutado><ans:procedimento><ans:codigoProcedimento>31003079</ans:codigoProcedimento></ans:procedimento></ans:procedimentoExecutado><ans:procedimentoExecutado><ans:procedimento><ans:codigoProcedimento>30912016</ans:codigoProcedimento></ans:procedimento></ans:procedimentoExecutado><ans:procedimentoExecutado><ans:procedimento><ans:codigoProcedimento>31005497</ans:codigoProcedimento></ans:procedimento></ans:procedimentoExecutado><ans:procedimentoExecutado><ans:procedimento><ans:codigoProcedimento>31005497</ans:codigoProcedimento></ans:procedimento></ans:procedimentoExecutado><ans:procedimentoExecutado><ans:procedimento><ans:codigoProcedimento>30912016</ans:codigoProcedimento></ans:procedimento></ans:procedimentoExecutado><ans:procedimentoExecutado><ans:procedimento><ans:codigoProcedimento>40803104</ans:codigoProcedimento></ans:procedimento></ans:procedimentoExecutado><ans:procedimentoExecutado><ans:procedimento><ans:codigoProcedimento>40803104</ans:codigoProcedimento></ans:procedimento></ans:procedimentoExecutado><ans:procedimentoExecutado><ans:procedimento><ans:codigoProcedimento>40304361</ans:codigoProcedimento></ans:procedimento></ans:procedimentoExecutado><ans:procedimentoExecutado><ans:procedimento><ans:codigoProcedimento>30912016</ans:codigoProcedimento></ans:procedimento></ans:procedimentoExecutado><ans:procedimentoExecutado><ans:procedimento><ans:codigoProcedimento>30912016</ans:codigoProcedimento></ans:procedimento></ans:procedimentoExecutado><ans:procedimentoExecutado><ans:procedimento><ans:codigoProcedimento>40304361</ans:codigoProcedimento></ans:procedimento></ans:procedimentoExecutado><ans:procedimentoExecutado><ans:procedimento><ans:codigoProcedimento>40304361</ans:codigoProcedimento></ans:procedimento></ans:procedimentoExecutado></ans:procedimentosExecutados><ans:valorTotal><ans:valorOPME>426.50</ans:valorOPME><ans:valorTotalGeral>5557.71</ans:valorTotalGeral></ans:valorTotal></ans:guiaResumoInternacao><ans:guiaResumoInternacao><ans:cabecalhoGuia><ans:registroANS>312345</ans:registroANS><ans:numeroGuiaPrestador>G00051</ans:numeroGuiaPrestador></ans:cabecalhoGuia><ans:dataInicioFaturamento>2025-04-17</ans:dataInicioFaturamento><ans:dataFinalFaturamento>2025-04-20</ans:dataFinalFaturamento><ans:diagnosticoCID><ans:codigoDiagnostico>I63.9</ans:codigoDiagnostico></ans:diagnosticoCID><ans:procedimentosExecutados><ans:procedimentoExecutado><ans:procedimento><ans:codigoProcedimento>41001010</ans:codigoProcedimento></ans:procedimento></ans:procedimentoExecutado><ans:procedimentoExecutado><ans:procedimento><ans:codigoProcedimento>31602096</ans:codigoProcedimento></ans:procedimento></ans:procedimentoExecutado><ans:procedimentoExecutado><ans:procedimento><ans:codigoProcedimento>40803104</ans:codigoProcedimento></ans:procedimento></ans:procedimentoExecutado><ans:procedimentoExecutado><ans:procedimento><ans:codigoProcedimento>30912016</ans:codigoProcedimento></ans:procedimento></ans:procedimentoExecutado><ans:procedimentoExecutado><ans:procedimento><ans:codigoProcedimento>31602096</ans:codigoProcedimento></ans:procedimento></ans:procedimentoExecutado><ans:procedimentoExecutado><ans:procedimento><ans:codigoProcedimento>40803104</ans:codigoProcedimento></ans:procedimento></ans:procedimentoExecutado><ans:procedimentoExecutado><ans:procedimento><ans:codigoProcedimento>31101011</ans:codigoProcedimento></ans:procedimento></ans:procedimentoExecutado></ans:procedimentosExecutados><ans:valorTotal><ans:valorOPME>136.76</ans:valorOPME><ans:valorTotalGeral>2862.77</ans:valorTotalGeral></ans:valorTotal></ans:guiaResumoInternacao><ans:guiaResumoInternacao><ans:cabecalhoGuia><ans:registroANS>312345</ans:registroANS><ans:numeroGuiaPrestador>G00052</ans:numeroGuiaPrestador></ans:cabecalhoGuia><ans:dataInicioFaturamento>2025-04-03</ans:dataInicioFaturamento><ans:dataFinalFaturamento>2025-04-08</ans:dataFinalFaturamento><ans:diagnosticoCID>A41.9</ans:diagnosticoCID><ans:procedimentosExecutados><ans:procedimentoExecutado><ans:procedimento><ans:codigoProcedimento>31101011</ans:codigoProcedimento></ans:procedimento></ans:procedimentoExecutado><ans:procedimentoExecutado><ans:procedimento><ans:codigoProcedimento>40304361</ans:codigoProcedimento></ans:procedimento></ans:procedimentoExecutado><ans:procedimentoExecutado><ans:procedimento><ans:codigoProcedimento>40803104</ans:codigoProcedimento></ans:procedimento></ans:procedimentoExecutado><ans:procedimentoExecutado><ans:procedimento><ans:codigoProcedimento>31101011</ans:codigoProcedimento></ans:procedimento></ans:procedimentoExecutado><ans:procedimentoExecutado><ans:procedimento><ans:codigoProcedimento>40803104</ans:codigoProcedimento></ans:procedimento></ans:procedimentoExecutado><ans:procedimentoExecutado><ans:procedimento><ans:codigoProcedimento>31005497</ans:codigoProcedimento></ans:procedimento></ans:procedimentoExecutado><ans:procedimentoExecutado><ans:procedimento><ans:codigoProcedimento>31003079</ans:codigoProcedimento></ans:procedimento></ans:procedimentoExecutado><ans:procedimentoExecutado><ans:procedimento><ans:codigoProcedimento>30213036</ans:codigoProcedimento></ans:procedimento></ans:procedimentoExecutado></ans:procedimentosExecutados><ans:valorTotal><ans:valorOPME>3979.67</ans:valorOPME><ans:valorTotalGeral>38512.58</ans:valorTotalGeral></ans:valorTotal></ans:guiaResumoInternacao><ans:guiaResumoInternacao><ans:cabecalhoGuia><ans:registroANS>312345</ans:registroANS><ans:numeroGuiaPrestador>G00053</ans:numeroGuiaPrestador></ans:cabecalhoGuia><ans:dataInicioFaturamento>2025-04-12</ans:dataInicioFaturamento><ans:dataFinalFaturamento>2025-04-13</ans:dataFinalFaturamento><ans:diagnosticoCID><ans:codigoDiagnostico>I50.0</ans:codigoDiagnostico></ans:diagnosticoCID><ans:procedimentosExecutados><ans:procedimentoExecutado><ans:procedimento><ans:codigoProcedimento>30213036</ans:codigoProcedimento></ans:procedimento></ans:procedimentoExecutado><ans:procedimentoExecutado><ans:procedimento><ans:codigoProcedimento>30213036</ans:codigoProcedimento></ans:procedimento></ans:procedimentoExecutado><ans:procedimentoExecutado><ans:procedimento><ans:codigoProcedimento>41001010</ans:codigoProcedimento></ans:procedimento></ans:procedimentoExecutado><ans:procedimentoExecutado><ans:procedimento><ans:codigoProcedimento>31005497</ans:codigoProcedimento></ans:procedimento></ans:procedimentoExecutado></ans:procedimentosExecutados><ans:valorTotal><ans:valorOPME>16.53</ans:valorOPME><ans:valorTotalGeral>2382.24</ans:valorTotalGeral></ans:valorTotal></ans:guiaResumoInternacao><ans:guiaResumoInternacao><ans:cabecalhoGuia><ans:registroANS>312345</ans:registroANS><ans:numeroGuiaPrestador>G00054</ans:numeroGuiaPrestador></ans:cabecalhoGuia><ans:dataInicioFaturamento>2025-04-01</ans:dataInicioFaturamento><ans:dataFinalFaturamento>2025-04-04</ans:dataFinalFaturamento><ans:diagnosticoCID><ans:codigoDiagnostico>C34.9</ans:codigoDiagnostico></ans:diagnosticoCID><ans:procedimentosExecutados><ans:procedimentoExecutado><ans:procedimento><ans:codigoProcedimento>31005497</ans:codigoProcedimento></ans:procedimento></ans:procedimentoExecutado><ans:procedimentoExecutado><ans:procedimento><ans:codigoProcedimento>40304361</ans:codigoProcedimento></ans:procedimento></ans:procedimentoExecutado><ans:procedimentoExecutado><ans:procedimento><ans:codigoProcedimento>41001010</ans:codigoProcedimento></ans:procedimento></ans:procedimentoExecutado><ans:procedimentoExecutado><ans:procedimento><ans:codigoProcedimento>31602096</ans:codigoProcedimento></ans:procedimento></ans:procedimentoExecutado><ans:procedimentoExecutado><ans:procedimento><ans:codigoProcedimento>40803104</ans:codigoProcedimento></ans:procedimento></ans:procedimentoExecutado></ans:procedimentosExecutados><ans:valorTotal><ans:valorOPME>521.33</ans:valorOPME><ans:valorTotalGeral>3059.02</ans:valorTotalGeral></ans:valorTotal></ans:guiaResumoInternacao><ans:guiaResumoInternacao><ans:cabecalhoGuia><ans:registroANS>312345</ans:registroANS><ans:numeroGuiaPrestador>G00055</ans:numeroGuiaPrestador></ans:cabecalhoGuia><ans:dataInicioFaturamento>2025-04-05</ans:dataInicioFaturamento><ans:dataFinalFaturamento>2025-04-11</ans:dataFinalFaturamento><ans:diagnosticoCID>N39.0</ans:diagnosticoCID><ans:procedimentosExecutados><ans:procedimentoExecutado><ans:procedimento><ans:codigoProcedimento>30912016</ans:codigoProcedimento></ans:procedimento></ans:procedimentoExecutado><ans:procedimentoExecutado><ans:procedimento><ans:codigoProcedimento>30213036</ans:codigoProcedimento></ans:procedimento></ans:procedimentoExecutado><ans:procedimentoExecutado><ans:procedimento><ans:codigoProcedimento>30912016</ans:codigoProcedimento></ans:procedimento></ans:procedimentoExecutado><ans:procedimentoExecutado><ans:procedimento><ans:codigoProcedimento>40803104</ans:codigoProcedimento></ans:procedimento></ans:procedimentoExecutado><ans:procedimentoExecutado><ans:procedimento><ans:codigoProcedimento>31003079</ans:codigoProcedimento></ans:procedimento></ans:procedimentoExecutado><ans:procedimentoExecutado><ans:procedimento><ans:codigoProcedimento>31602096</ans:codigoProcedimento></ans:procedimento></ans:procedimentoExecutado><ans:procedimentoExecutado><ans:procedimento><ans:codigoProcedimento>41001010</ans:codigoProcedimento></ans:procedimento></ans:procedimentoExecutado><ans:procedimentoExecutado><ans:procedimento><ans:codigoProcedimento>40304361</ans:codigoProcedimento></ans:procedimento></ans:procedimentoExecutado></ans:procedimentosExecutados><ans:valorTotal><ans:valorOPME>249.97</ans:valorOPME><ans:valorTotalGeral>1360.90</ans:valorTotalGeral></ans:valorTotal></ans:guiaResumoInternacao><ans:guiaResumoInternacao><ans:cabecalhoGuia><ans:registroANS>312345</ans:registroANS><ans:numeroGuiaPrestador>G00056</ans:numeroGuiaPrestador></ans:cabecalhoGuia><ans:dataInicioFaturamento>2025-04-20</ans:dataInicioFaturamento><ans:dataFinalFaturamento>2025-04-21</ans:dataFinalFaturamento><ans:diagnosticoCID><ans:codigoDiagnostico>O80</ans:codigoDiagnostico></ans:diagnosticoCID><ans:procedimentosExecutados><ans:procedimentoExecutado><ans:procedimento><ans:codigoProcedimento>30715016</ans:codigoProcedimento></ans:procedimento></ans:procedimentoExecutado><ans:procedimentoExecutado><ans:procedimento><ans:codigoProcedimento>40803104</ans:codigoProcedimento></ans:procedimento></ans:procedimentoExecutado><ans:procedimentoExecutado><ans:procedimento><ans:codigoProcedimento>41001010</ans:codigoProcedimento></ans:procedimento></ans:procedimentoExecutado><ans:procedimentoExecutado><ans:procedimento><ans:codigoProcedimento>31602096</ans:codigoProcedimento></ans:procedimento></ans:procedimentoExecutado></ans:procedimentosExecutados><ans:valorTotal><ans:valorOPME>9.99</ans:valorOPME><ans:valorTotalGeral>9643.13</ans:valorTotalGeral></ans:valorTotal></ans:guiaResumoInternacao><ans:guiaResumoInternacao><ans:cabecalhoGuia><ans:registroANS>312345</ans:registroANS><ans:numeroGuiaPrestador>G00057</ans:numeroGuiaPrestador></ans:cabecalhoGuia><ans:dataInicioFaturamento>2025-04-03</ans:dataInicioFaturamento><ans:dataFinalFaturamento>2025-04-07</ans:dataFinalFaturamento><ans:diagnosticoCID>S72.0</ans:diagnosticoCID><ans:procedimentosExecutados><ans:procedimentoExecutado><ans:procedimento><ans:codigoProcedimento>40304361</ans:codigoProcedimento></ans:procedimento></ans:procedimentoExecutado><ans:procedimentoExecutado><ans:procedimento><ans:codigoProcedimento>40803104</ans:codigoProcedimento></ans:procedimento></ans:procedimentoExecutado><ans:procedimentoExecutado><ans:procedimento><ans:codigoProcedimento>31005497</ans:codigoProcedimento></ans:procedimento></ans:procedimentoExecutado><ans:procedimentoExecutado><ans:procedimento><ans:codigoProcedimento>31101011</ans:codigoProcedimento></ans:procedimento></ans:procedimentoExecutado><ans:procedimentoExecutado><ans:procedimento><ans:codigoProcedimento>30715016</ans:codigoProcedimento></ans:procedimento></ans:procedimentoExecutado><ans:procedimentoExecutado><ans:procedimento><ans:codigoProcedimento>30213036</ans:codigoProcedimento></ans:procedimento></ans:procedimentoExecutado><ans:procedimentoExecutado><ans:procedimento><ans:codigoProcedimento>30912016</ans:codigoProcedimento></ans:procedimento></ans:procedimentoExecutado><ans:procedimentoExecutado><ans:procedimento><ans:codigoProcedimento>31101011</ans:codigoProcedimento></ans:procedimento></ans:procedimentoExecutado></ans:procedimentosExecutados><ans:valorTotal><ans:valorOPME>2295.06</ans:valorOPME><ans:valorTotalGeral>20289.47</ans:valorTotalGeral></ans:valorTotal></ans:guiaResumoInternacao><ans:guiaResumoInternacao><ans:cabecalhoGuia><ans:registroANS>312345</ans:registroANS><ans:numeroGuiaPrestador>G00058</ans:numeroGuiaPrestador></ans:cabecalhoGuia><ans:dataInicioFaturamento>2025-04-08</ans:dataInicioFaturamento><ans:dataFinalFaturamento>2025-04-23</ans:dataFinalFaturamento><ans:diagnosticoCID>I63.9</ans:diagnosticoCID><ans:procedimentosExecutados><ans:procedimentoExecutado><ans:procedimento><ans:codigoProcedimento>31101011</ans:codigoProcedimento></ans:procedimento></ans:procedimentoExecutado><ans:procedimentoExecutado><ans:procedimento><ans:codigoProcedimento>31101011</ans:codigoProcedimento></ans:procedimento></ans:procedimentoExecutado><ans:procedimentoExecutado><ans:procedimento><ans:codigoProcedimento>30715016</ans:codigoProcedimento></ans:procedimento></ans:procedimentoExecutado><ans:procedimentoExecutado><ans:procedimento><ans:codigoProcedimento>31602096</ans:codigoProcedimento></ans:procedimento></ans:procedimentoExecutado><ans:procedimentoExecutado><ans:procedimento><ans:codigoProcedimento>40304361</ans:codigoProcedimento></ans:procedimento></ans:procedimentoExecutado><ans:procedimentoExecutado><ans:procedimento><ans:codigoProcedimento>30715016</ans:codigoProcedimento></ans:procedimento></ans:procedimentoExecutado><ans:procedimentoExecutado><ans:procedimento><ans:codigoProcedimento>31003079</ans:codigoProcedimento></ans:procedimento></ans:procedimentoExecutado><ans:procedimentoExecutado><ans:procedimento><ans:codigoProcedimento>31602096</ans:codigoProcedimento></ans:procedimento></ans:procedimentoExecutado><ans:procedimentoExecutado><ans:procedimento><ans:codigoProcedimento>30715016</ans:codigoProcedimento></ans:procedimento></ans:procedimentoExecutado><ans:procedimentoExecutado><ans:procedimento><ans:codigoProcedimento>30213036</ans:codigoProcedimento></ans:procedimento></ans:procedimentoExecutado><ans:procedimentoExecutado><ans:procedimento><ans:codigoProcedimento>30715016</ans:codigoProcedimento></ans:procedimento></ans:procedimentoExecutado><ans:procedimentoExecutado><ans:procedimento><ans:codigoProcedimento>40304361</ans:codigoProcedimento></ans:procedimento></ans:procedimentoExecutado><ans:procedimentoExecutado><ans:procedimento><ans:codigoProcedimento>30715016</ans:codigoProcedimento></ans:procedimento></ans:procedimentoExecutado><ans:procedimentoExecutado><ans:procedimento><ans:codigoProcedimento>30912016</ans:codigoProcedimento></ans:procedimento></ans:procedimentoExecutado></ans:procedimentosExecutados><ans:valorTotal><ans:valorOPME>318.03</ans:valorOPME><ans:valorTotalGeral>3984.51</ans:valorTotalGeral></ans:valorTotal></ans:guiaResumoInternacao><ans:guiaResumoInternacao><ans:cabecalhoGuia><ans:registroANS>312345</ans:registroANS><ans:numeroGuiaPrestador>G00059</ans:numeroGuiaPrestador></ans:cabecalhoGuia><ans:dataInicioFaturamento>2025-04-11</ans:dataInicioFaturamento><ans:dataFinalFaturamento>2025-04-18</ans:dataFinalFaturamento><ans:diagnosticoCID>S72.0</ans:diagnosticoCID><ans:procedimentosExecutados><ans:procedimentoExecutado><ans:procedimento><ans:codigoProcedimento>31003079</ans:codigoProcedimento></ans:procedimento></ans:procedimentoExecutado><ans:procedimentoExecutado><ans:procedimento><ans:codigoProcedimento>30912016</ans:codigoProcedimento></ans:procedimento></ans:procedimentoExecutado><ans:procedimentoExecutado><ans:procedimento><ans:codigoProcedimento>30912016</ans:codigoProcedimento></ans:procedimento></ans:procedimentoExecutado><ans:procedimentoExecutado><ans:procedimento><ans:codigoProcedimento>31005497</ans:codigoProcedimento></ans:procedimento></ans:procedimentoExecutado><ans:procedimentoExecutado><ans:procedimento><ans:codigoProcedimento>31005497</ans:codigoProcedimento></ans:procedimento></ans:procedimentoExecutado><ans:procedimentoExecutado><ans:procedimento><ans:codigoProcedimento>31101011</ans:codigoProcedimento></ans:procedimento></ans:procedimentoExecutado><ans:procedimentoExecutado><ans:procedimento><ans:codigoProcedimento>31003079</ans:codigoProcedimento></ans:procedimento></ans:procedimentoExecutado><ans:procedimentoExecutado><ans:procedimento><ans:codigoProcedimento>40304361</ans:codigoProcedimento></ans:procedimento></ans:procedimentoExecutado></ans:procedimentosExecutados><ans:valorTotal><ans:valorOPME>59.42</ans:valorOPME><ans:valorTotalGeral>4779.13</ans:valorTotalGeral></ans:valorTotal></ans:guiaResumoInternacao><ans:guiaResumoInternacao><ans:cabecalhoGuia><ans:registroANS>312345</ans:registroANS><ans:numeroGuiaPrestador>G00060</ans:numeroGuiaPrestador></ans:cabecalhoGuia><ans:dataInicioFaturamento>2025-04-11</ans:dataInicioFaturamento><ans:dataFinalFaturamento>2025-04-23</ans:dataFinalFaturamento><ans:diagnosticoCID>N39.0</ans:diagnosticoCID><ans:procedimentosExecutados><ans:procedimentoExecutado><ans:procedimento><ans:codigoProcedimento>31101011</ans:codigoProcedimento></ans:procedimento></ans:procedimentoExecutado><ans:procedimentoExecutado><ans:procedimento><ans:codigoProcedimento>40304361</ans:codigoProcedimento></ans:procedimento></ans:procedimentoExecutado><ans:procedimentoExecutado><ans:procedimento><ans:codigoProcedimento>41001010</ans:codigoProcedimento></ans:procedimento></ans:procedimentoExecutado><ans:procedimentoExecutado><ans:procedimento><ans:codigoProcedimento>30715016</ans:codigoProcedimento></ans:procedimento></ans:procedimentoExecutado><ans:procedimentoExecutado><ans:procedimento><ans:codigoProcedimento>31005497</ans:codigoProcedimento></ans:procedimento></ans:procedimentoExecutado><ans:procedimentoExecutado><ans:procedimento><ans:codigoProcedimento>31602096</ans:codigoProcedimento></ans:procedimento></ans:procedimentoExecutado><ans:procedimentoExecutado><ans:procedimento><ans:codigoProcedimento>30912016</ans:codigoProcedimento></ans:procedimento></ans:procedimentoExecutado><ans:procedimentoExecutado><ans:procedimento><ans:codigoProcedimento>30912016</ans:codigoProcedimento></ans:procedimento></ans:procedimentoExecutado><ans:procedimentoExecutado><ans:procedimento><ans:codigoProcedimento>41001010</ans:codigoProcedimento></ans:procedimento></ans:procedimentoExecutado><ans:procedimentoExecutado><ans:procedimento><ans:codigoProcedimento>41001010</ans:codigoProcedimento></ans:procedimento></ans:procedimentoExecutado><ans:procedimentoExecutado><ans:procedimento><ans:codigoProcedimento>30213036</ans:codigoProcedimento></ans:procedimento></ans:procedimentoExecutado><ans:procedimentoExecutado><ans:procedimento><ans:codigoProcedimento>30715016</ans:codigoProcedimento></ans:procedimento></ans:procedimentoExecutado><ans:procedimentoExecutado><ans:procedimento><ans:codigoProcedimento>31101011</ans:codigoProcedimento></ans:procedimento></ans:procedimentoExecutado></ans:procedimentosExecutados><ans:valorTotal><ans:valorOPME>3962.87</ans:valorOPME><ans:valorTotalGeral>7518.65</ans:valorTotalGeral></ans:valorTotal></ans:guiaResumoInternacao><ans:guiaResumoInternacao><ans:cabecalhoGuia><ans:registroANS>312345</ans:registroANS><ans:numeroGuiaPrestador>G00061</ans:numeroGuiaPrestador></ans:cabecalhoGuia><ans:dataInicioFaturamento>2025-04-11</ans:dataInicioFaturamento><ans:dataFinalFaturamento>2025-04-18</ans:dataFinalFaturamento><ans:diagnosticoCID>C34.9</ans:diagnosticoCID><ans:procedimentosExecutados><ans:procedimentoExecutado><ans:procedimento><ans:codigoProcedimento>30715016</ans:codigoProcedimento></ans:procedimento></ans:procedimentoExecutado><ans:procedimentoExecutado><ans:procedimento><ans:codigoProcedimento>31101011</ans:codigoProcedimento></ans:procedimento></ans:procedimentoExecutado><ans:procedimentoExecutado><ans:procedimento><ans:codigoProcedimento>31003079</ans:codigoProcedimento></ans:procedimento></ans:procedimentoExecutado><ans:procedimentoExecutado><ans:procedimento><ans:codigoProcedimento>40803104</ans:codigoProcedimento></ans:procedimento></ans:procedimentoExecutado><ans:procedimentoExecutado><ans:procedimento><ans:codigoProcedimento>30715016</ans:codigoProcedimento></ans:procedimento></ans:procedimentoExecutado><ans:procedimentoExecutado><ans:procedimento><ans:codigoProcedimento>30213036</ans:codigoProcedimento></ans:procedimento></ans:procedimentoExecutado><ans:procedimentoExecutado><ans:procedimento><ans:codigoProcedimento>40304361</ans:codigoProcedimento></ans:procedimento></ans:procedimentoExecutado><ans:procedimentoExecutado><ans:procedimento><ans:codigoProcedimento>31003079</ans:codigoProcedimento></ans:procedimento></ans:procedimentoExecutado><ans:procedimentoExecutado><ans:procedimento><ans:codigoProcedimento>41001010</ans:codigoProcedimento></ans:procedimento></ans:procedimentoExecutado></ans:procedimentosExecutados><ans:valorTotal><ans:valorOPME>276.06</ans:valorOPME><ans:valorTotalGeral>1625.64</ans:valorTotalGeral></ans:valorTotal></ans:guiaResumoInternacao><ans:guiaResumoInternacao><ans:cabecalhoGuia><ans:registroANS>312345</ans:registroANS><ans:numeroGuiaPrestador>G00062</ans:numeroGuiaPrestador></ans:cabecalhoGuia><ans:dataInicioFaturamento>2025-04-17</ans:dataInicioFaturamento><ans:dataFinalFaturamento>2025-04-18</ans:dataFinalFaturamento><ans:diagnosticoCID>J18.9</ans:diagnosticoCID><ans:procedimentosExecutados><ans:procedimentoExecutado><ans:procedimento><ans:codigoProcedimento>30912016</ans:codigoProcedimento></ans:procedimento></ans:procedimentoExecutado><ans:procedimentoExecutado><ans:procedimento><ans:codigoProcedimento>31602096</ans:codigoProcedimento></ans:procedimento></ans:procedimentoExecutado><ans:procedimentoExecutado><ans:procedimento><ans:codigoProcedimento>31602096</ans:codigoProcedimento></ans:procedimento></ans:procedimentoExecutado></ans:procedimentosExecutados><ans:valorTotal><ans:valorOPME>13.66</ans:valorOPME><ans:valorTotalGeral>3886.67</ans:valorTotalGeral></ans:valorTotal></ans:guiaResumoInternacao><ans:guiaResumoInternacao><ans:cabecalhoGuia><ans:registroANS>312345</ans:registroANS><ans:numeroGuiaPrestador>G00063</ans:numeroGuiaPrestador></ans:cabecalhoGuia><ans:dataInicioFaturamento>2025-04-11</ans:dataInicioFaturamento><ans:dataFinalFaturamento>2025-04-20</ans:dataFinalFaturamento><ans:diagnosticoCID>I63.9</ans:diagnosticoCID><ans:procedimentosExecutados><ans:procedimentoExecutado><ans:procedimento><ans:codigoProcedimento>30213036</ans:codigoProcedimento></ans:procedimento></ans:procedimentoExecutado><ans:procedimentoExecutado><ans:procedimento><ans:codigoProcedimento>30715016</ans:codigoProcedimento></ans:procedimento></ans:procedimentoExecutado><ans:procedimentoExecutado><ans:procedimento><ans:codigoProcedimento>30912016</ans:codigoProcedimento></ans:procedimento></ans:procedimentoExecutado><ans:procedimentoExecutado><ans:procedimento><ans:codigoProcedimento>31005497</ans:codigoProcedimento></ans:procedimento></ans:procedimentoExecutado><ans:procedimentoExecutado><ans:procedimento><ans:codigoProcedimento>40803104</ans:codigoProcedimento></ans:procedimento></ans:procedimentoExecutado><ans:procedimentoExecutado><ans:procedimento><ans:codigoProcedimento>31101011</ans:codigoProcedimento></ans:procedimento></ans:procedimentoExecutado><ans:procedimentoExecutado><ans:procedimento><ans:codigoProcedimento>31602096</ans:codigoProcedimento></ans:procedimento></ans:procedimentoExecutado><ans:procedimentoExecutado><ans:procedimento><ans:codigoProcedimento>30912016</ans:codigoProcedimento></ans:procedimento></ans:procedimentoExecutado><ans:procedimentoExecutado><ans:procedimento><ans:codigoProcedimento>30213036</ans:codigoProcedimento></ans:procedimento></ans:procedimentoExecutado><ans:procedimentoExecutado><ans:procedimento><ans:codigoProcedimento>31003079</ans:codigoProcedimento></ans:procedimento></ans:procedimentoExecutado></ans:procedimentosExecutados><ans:valorTotal><ans:valorOPME>3179.04</ans:valorOPME><ans:valorTotalGeral>24870.48</ans:valorTotalGeral></ans:valorTotal></ans:guiaResumoInternacao><ans:guiaResumoInternacao><ans:cabecalhoGuia><ans:registroANS>312345</ans:registroANS><ans:numeroGuiaPrestador>G00064</ans:numeroGuiaPrestador></ans:cabecalhoGuia><ans:dataInicioFaturamento>2025-04-19</ans:dataInicioFaturamento><ans:dataFinalFaturamento>2025-04-21</ans:dataFinalFaturamento><ans:diagnosticoCID><ans:codigoDiagnostico>I21.0</ans:codigoDiagnostico></ans:diagnosticoCID><ans:procedimentosExecutados><ans:procedimentoExecutado><ans:procedimento><ans:codigoProcedimento>30715016</ans:codigoProcedimento></ans:procedimento></ans:procedimentoExecutado><ans:procedimentoExecutado><ans:procedimento><ans:codigoProcedimento>31602096</ans:codigoProcedimento></ans:procedimento></ans:procedimentoExecutado><ans:procedimentoExecutado><ans:procedimento><ans:codigoProcedimento>30213036</ans:codigoProcedimento></ans:procedimento></ans:procedimentoExecutado><ans:procedimentoExecutado><ans:procedimento><ans:codigoProcedimento>30715016</ans:codigoProcedimento></ans:procedimento></ans:procedimentoExecutado><ans:procedimentoExecutado><ans:procedimento><ans:codigoProcedimento>31003079</ans:codigoProcedimento></ans:procedimento></ans:procedimentoExecutado></ans:procedimentosExecutados><ans:valorTotal><ans:valorOPME>292.55</ans:valorOPME><ans:valorTotalGeral>21795.07</ans:valorTotalGeral></ans:valorTotal></ans:guiaResumoInternacao></ans:loteGuias></ans:mensagemTISS>